{"nodes": [{"id": "app_notifications_ts", "label": "notifications.ts", "file_type": "code", "source_file": "app\\notifications.ts", "source_location": "L1"}, {"id": "notifications_getdayindex", "label": "getDayIndex()", "file_type": "code", "source_file": "app\\notifications.ts", "source_location": "L10"}, {"id": "notifications_getnotifications", "label": "getNotifications()", "file_type": "code", "source_file": "app\\notifications.ts", "source_location": "L14"}, {"id": "notifications_requestnotificationpermission", "label": "requestNotificationPermission()", "file_type": "code", "source_file": "app\\notifications.ts", "source_location": "L33"}, {"id": "notifications_scheduledailyreminder", "label": "scheduleDailyReminder()", "file_type": "code", "source_file": "app\\notifications.ts", "source_location": "L69"}, {"id": "notifications_cancelallnotifications", "label": "cancelAllNotifications()", "file_type": "code", "source_file": "app\\notifications.ts", "source_location": "L107"}, {"id": "notifications_sendstreakwarning", "label": "sendStreakWarning()", "file_type": "code", "source_file": "app\\notifications.ts", "source_location": "L117"}, {"id": "notifications_sendpremiumnotification", "label": "sendPremiumNotification()", "file_type": "code", "source_file": "app\\notifications.ts", "source_location": "L141"}, {"id": "notifications_loadnotifsettings", "label": "loadNotifSettings()", "file_type": "code", "source_file": "app\\notifications.ts", "source_location": "L170"}, {"id": "notifications_savenotifsettings", "label": "saveNotifSettings()", "file_type": "code", "source_file": "app\\notifications.ts", "source_location": "L178"}, {"id": "notifications_schedulenotifications", "label": "scheduleNotifications()", "file_type": "code", "source_file": "app\\notifications.ts", "source_location": "L184"}, {"id": "notifications_schedulestreakwarningifneeded", "label": "scheduleStreakWarningIfNeeded()", "file_type": "code", "source_file": "app\\notifications.ts", "source_location": "L198"}, {"id": "notifications_scheduleweeklyrecapnotification", "label": "scheduleWeeklyRecapNotification()", "file_type": "code", "source_file": "app\\notifications.ts", "source_location": "L284"}, {"id": "notifications_schedulemonthlyrecapnotification", "label": "scheduleMonthlyRecapNotification()", "file_type": "code", "source_file": "app\\notifications.ts", "source_location": "L325"}, {"id": "notifications_checkleagueovertakenotification", "label": "checkLeagueOvertakeNotification()", "file_type": "code", "source_file": "app\\notifications.ts", "source_location": "L365"}, {"id": "notifications_loadnotificationsettings", "label": "loadNotificationSettings()", "file_type": "code", "source_file": "app\\notifications.ts", "source_location": "L401"}, {"id": "notifications_schedulephrasofdaynotification", "label": "schedulePhrasOfDayNotification()", "file_type": "code", "source_file": "app\\notifications.ts", "source_location": "L424"}, {"id": "notifications_setupnotificationtaphandler", "label": "setupNotificationTapHandler()", "file_type": "code", "source_file": "app\\notifications.ts", "source_location": "L489"}], "edges": [{"source": "app_notifications_ts", "target": "react_native", "relation": "imports_from", "confidence": "EXTRACTED", "source_file": "app\\notifications.ts", "source_location": "L6", "weight": 1.0}, {"source": "app_notifications_ts", "target": "async_storage", "relation": "imports_from", "confidence": "EXTRACTED", "source_file": "app\\notifications.ts", "source_location": "L7", "weight": 1.0}, {"source": "app_notifications_ts", "target": "daily_phrase_system", "relation": "imports_from", "confidence": "EXTRACTED", "source_file": "app\\notifications.ts", "source_location": "L8", "weight": 1.0}, {"source": "app_notifications_ts", "target": "notifications_getdayindex", "relation": "contains", "confidence": "EXTRACTED", "source_file": "app\\notifications.ts", "source_location": "L10", "weight": 1.0}, {"source": "app_notifications_ts", "target": "notifications_getnotifications", "relation": "contains", "confidence": "EXTRACTED", "source_file": "app\\notifications.ts", "source_location": "L14", "weight": 1.0}, {"source": "app_notifications_ts", "target": "notifications_requestnotificationpermission", "relation": "contains", "confidence": "EXTRACTED", "source_file": "app\\notifications.ts", "source_location": "L33", "weight": 1.0}, {"source": "app_notifications_ts", "target": "notifications_scheduledailyreminder", "relation": "contains", "confidence": "EXTRACTED", "source_file": "app\\notifications.ts", "source_location": "L69", "weight": 1.0}, {"source": "app_notifications_ts", "target": "notifications_cancelallnotifications", "relation": "contains", "confidence": "EXTRACTED", "source_file": "app\\notifications.ts", "source_location": "L107", "weight": 1.0}, {"source": "app_notifications_ts", "target": "notifications_sendstreakwarning", "relation": "contains", "confidence": "EXTRACTED", "source_file": "app\\notifications.ts", "source_location": "L117", "weight": 1.0}, {"source": "app_notifications_ts", "target": "notifications_sendpremiumnotification", "relation": "contains", "confidence": "EXTRACTED", "source_file": "app\\notifications.ts", "source_location": "L141", "weight": 1.0}, {"source": "app_notifications_ts", "target": "notifications_loadnotifsettings", "relation": "contains", "confidence": "EXTRACTED", "source_file": "app\\notifications.ts", "source_location": "L170", "weight": 1.0}, {"source": "app_notifications_ts", "target": "notifications_savenotifsettings", "relation": "contains", "confidence": "EXTRACTED", "source_file": "app\\notifications.ts", "source_location": "L178", "weight": 1.0}, {"source": "app_notifications_ts", "target": "notifications_schedulenotifications", "relation": "contains", "confidence": "EXTRACTED", "source_file": "app\\notifications.ts", "source_location": "L184", "weight": 1.0}, {"source": "app_notifications_ts", "target": "notifications_schedulestreakwarningifneeded", "relation": "contains", "confidence": "EXTRACTED", "source_file": "app\\notifications.ts", "source_location": "L198", "weight": 1.0}, {"source": "app_notifications_ts", "target": "notifications_scheduleweeklyrecapnotification", "relation": "contains", "confidence": "EXTRACTED", "source_file": "app\\notifications.ts", "source_location": "L284", "weight": 1.0}, {"source": "app_notifications_ts", "target": "notifications_schedulemonthlyrecapnotification", "relation": "contains", "confidence": "EXTRACTED", "source_file": "app\\notifications.ts", "source_location": "L325", "weight": 1.0}, {"source": "app_notifications_ts", "target": "notifications_checkleagueovertakenotification", "relation": "contains", "confidence": "EXTRACTED", "source_file": "app\\notifications.ts", "source_location": "L365", "weight": 1.0}, {"source": "app_notifications_ts", "target": "notifications_loadnotificationsettings", "relation": "contains", "confidence": "EXTRACTED", "source_file": "app\\notifications.ts", "source_location": "L401", "weight": 1.0}, {"source": "app_notifications_ts", "target": "notifications_schedulephrasofdaynotification", "relation": "contains", "confidence": "EXTRACTED", "source_file": "app\\notifications.ts", "source_location": "L424", "weight": 1.0}, {"source": "app_notifications_ts", "target": "notifications_setupnotificationtaphandler", "relation": "contains", "confidence": "EXTRACTED", "source_file": "app\\notifications.ts", "source_location": "L489", "weight": 1.0}, {"source": "notifications_requestnotificationpermission", "target": "notifications_getnotifications", "relation": "calls", "confidence": "EXTRACTED", "source_file": "app\\notifications.ts", "source_location": "L35", "weight": 1.0}, {"source": "notifications_scheduledailyreminder", "target": "notifications_getnotifications", "relation": "calls", "confidence": "EXTRACTED", "source_file": "app\\notifications.ts", "source_location": "L75", "weight": 1.0}, {"source": "notifications_scheduledailyreminder", "target": "notifications_requestnotificationpermission", "relation": "calls", "confidence": "EXTRACTED", "source_file": "app\\notifications.ts", "source_location": "L78", "weight": 1.0}, {"source": "notifications_cancelallnotifications", "target": "notifications_getnotifications", "relation": "calls", "confidence": "EXTRACTED", "source_file": "app\\notifications.ts", "source_location": "L109", "weight": 1.0}, {"source": "notifications_sendstreakwarning", "target": "notifications_getnotifications", "relation": "calls", "confidence": "EXTRACTED", "source_file": "app\\notifications.ts", "source_location": "L119", "weight": 1.0}, {"source": "notifications_sendstreakwarning", "target": "notifications_requestnotificationpermission", "relation": "calls", "confidence": "EXTRACTED", "source_file": "app\\notifications.ts", "source_location": "L122", "weight": 1.0}, {"source": "notifications_sendpremiumnotification", "target": "notifications_getnotifications", "relation": "calls", "confidence": "EXTRACTED", "source_file": "app\\notifications.ts", "source_location": "L143", "weight": 1.0}, {"source": "notifications_sendpremiumnotification", "target": "notifications_requestnotificationpermission", "relation": "calls", "confidence": "EXTRACTED", "source_file": "app\\notifications.ts", "source_location": "L145", "weight": 1.0}, {"source": "notifications_schedulenotifications", "target": "notifications_cancelallnotifications", "relation": "calls", "confidence": "EXTRACTED", "source_file": "app\\notifications.ts", "source_location": "L190", "weight": 1.0}, {"source": "notifications_schedulenotifications", "target": "notifications_scheduledailyreminder", "relation": "calls", "confidence": "EXTRACTED", "source_file": "app\\notifications.ts", "source_location": "L192", "weight": 1.0}, {"source": "notifications_schedulestreakwarningifneeded", "target": "notifications_getnotifications", "relation": "calls", "confidence": "EXTRACTED", "source_file": "app\\notifications.ts", "source_location": "L200", "weight": 1.0}, {"source": "notifications_schedulestreakwarningifneeded", "target": "notifications_requestnotificationpermission", "relation": "calls", "confidence": "EXTRACTED", "source_file": "app\\notifications.ts", "source_location": "L202", "weight": 1.0}, {"source": "notifications_scheduleweeklyrecapnotification", "target": "notifications_getnotifications", "relation": "calls", "confidence": "EXTRACTED", "source_file": "app\\notifications.ts", "source_location": "L286", "weight": 1.0}, {"source": "notifications_scheduleweeklyrecapnotification", "target": "notifications_requestnotificationpermission", "relation": "calls", "confidence": "EXTRACTED", "source_file": "app\\notifications.ts", "source_location": "L288", "weight": 1.0}, {"source": "notifications_schedulemonthlyrecapnotification", "target": "notifications_getnotifications", "relation": "calls", "confidence": "EXTRACTED", "source_file": "app\\notifications.ts", "source_location": "L327", "weight": 1.0}, {"source": "notifications_schedulemonthlyrecapnotification", "target": "notifications_requestnotificationpermission", "relation": "calls", "confidence": "EXTRACTED", "source_file": "app\\notifications.ts", "source_location": "L329", "weight": 1.0}, {"source": "notifications_checkleagueovertakenotification", "target": "notifications_getnotifications", "relation": "calls", "confidence": "EXTRACTED", "source_file": "app\\notifications.ts", "source_location": "L371", "weight": 1.0}, {"source": "notifications_checkleagueovertakenotification", "target": "notifications_requestnotificationpermission", "relation": "calls", "confidence": "EXTRACTED", "source_file": "app\\notifications.ts", "source_location": "L383", "weight": 1.0}, {"source": "notifications_schedulephrasofdaynotification", "target": "notifications_getnotifications", "relation": "calls", "confidence": "EXTRACTED", "source_file": "app\\notifications.ts", "source_location": "L426", "weight": 1.0}, {"source": "notifications_schedulephrasofdaynotification", "target": "notifications_requestnotificationpermission", "relation": "calls", "confidence": "EXTRACTED", "source_file": "app\\notifications.ts", "source_location": "L428", "weight": 1.0}, {"source": "notifications_schedulephrasofdaynotification", "target": "notifications_getdayindex", "relation": "calls", "confidence": "EXTRACTED", "source_file": "app\\notifications.ts", "source_location": "L467", "weight": 1.0}, {"source": "notifications_setupnotificationtaphandler", "target": "notifications_getnotifications", "relation": "calls", "confidence": "EXTRACTED", "source_file": "app\\notifications.ts", "source_location": "L493", "weight": 1.0}]}